telebot/__init__.py
telebot/api/__init__.py
telebot/api/exceptions.py
telebot/api/request.py
telebot/base/__init__.py
telebot/base/base_document.py
telebot/base/base_model.py
telebot/base/constants.py
telebot/base/exceptions.py
telebot/base/new_object.py
telebot/base/tg_method.py
telebot/base/tg_object.py
telebot/base/user_proxy_model.py
telebot/context/__init__.py
telebot/context/context_dict.py
telebot/context/layer0.py
telebot/context/layer1.py
telebot/context/layer2.py
telebot/context/layer3.py
telebot/context/storage.py
telebot/filters/__init__.py
telebot/filters/base.py
telebot/filters/button.py
telebot/filters/callback_query.py
telebot/filters/chat_type.py
telebot/filters/message.py
telebot/filters/state.py
telebot/filters/user_id.py
telebot/handlers/__init__.py
telebot/handlers/base.py
telebot/handlers/button.py
telebot/handlers/callback_query.py
telebot/handlers/command.py
telebot/handlers/contact.py
telebot/handlers/document.py
telebot/handlers/photo.py
telebot/handlers/text.py
telebot/loader.py
telebot/objects/__init__.py
telebot/objects/new/__init__.py
telebot/objects/new/callback_button.py
telebot/objects/new/inline_keyboard.py
telebot/objects/new/keyboard.py
telebot/objects/new/translations.py
telebot/objects/new/url_button.py
telebot/objects/tg_methods.py
telebot/objects/tg_objects.py
telebot/requests/__init__.py
telebot/requests/answer_callback_query.py
telebot/requests/base.py
telebot/requests/edit_message_text.py
telebot/requests/get_file.py
telebot/requests/get_me.py
telebot/requests/get_updates.py
telebot/requests/send_chat_action.py
telebot/requests/send_message.py
telebot/requests/send_video.py
telebot/requests/set_my_commands.py
telebot/run/__init__.py
telebot/run/main.py
telebot/utils/__init__.py
telebot/utils/cast.py
telebot/utils/clean_dict.py
telebot/utils/listify.py
bebrogram-0.1.1.dist-info/WHEEL
bebrogram-0.1.1.dist-info/METADATA
bebrogram-0.1.1.dist-info/RECORD
