Metadata-Version: 2.1
Name: bebrogram
Version: 0.1.1
Summary: 
Requires-Python: >=3.10,<4.0
Classifier: Programming Language :: Python :: 3
Classifier: Programming Language :: Python :: 3.10
Requires-Dist: envparse (>=0.2.0,<0.3.0)
Requires-Dist: mongoengine (>=0.24.2,<0.25.0)
Requires-Dist: requests (>=2.28.1,<3.0.0)
